preisach.py
preisach-0.0.1.dist-info/LICENSE
preisach-0.0.1.dist-info/METADATA
preisach-0.0.1.dist-info/WHEEL
preisach-0.0.1.dist-info/top_level.txt
preisach-0.0.1.dist-info/RECORD
